parcelhub/__init__.py
parcelhub/client.py
parcelhub/exceptions.py
parcelhub_api_client-0.3.0.dist-info/LICENSE
parcelhub_api_client-0.3.0.dist-info/METADATA
parcelhub_api_client-0.3.0.dist-info/WHEEL
parcelhub_api_client-0.3.0.dist-info/top_level.txt
parcelhub_api_client-0.3.0.dist-info/RECORD
